funscnet/__init__.py
funscnet/api/__init__.py
funscnet/api/base.py
funscnet/api/constant.py
funscnet/api/container.py
funscnet/api/file.py
funscnet/api/job.py
funscnet/api/merge.py
funscnet/api/token.py
funscnet-1.0.6.dist-info/METADATA
funscnet-1.0.6.dist-info/WHEEL
funscnet-1.0.6.dist-info/top_level.txt
funscnet-1.0.6.dist-info/RECORD
