Metadata-Version: 2.4
Name: funscnet
Version: 1.0.6
Summary: funscnet
Author-email: 牛哥 <niuliangtao@qq.com>, farfarfun <farfarfun@qq.com>
Maintainer-email: 牛哥 <niuliangtao@qq.com>, farfarfun <farfarfun@qq.com>
Project-URL: Organization, https://github.com/farfarfun
Project-URL: Repository, https://github.com/farfarfun/funscnet
Project-URL: Releases, https://github.com/farfarfun/funscnet/releases
Requires-Python: >=3.8
